{
  "slug": "bassil-hafez",
  "name": "Bassil Hafez",
  "last_updated": "2026-04-28T18:36:34.295716",
  "weight_class": "Welterweight",
  "record": "1-2-0",
  "wins": 1,
  "losses": 2,
  "draws": 0,
  "height": "5' 11\"",
  "reach": "72\"",
  "weight_lbs": "170 lbs",
  "stance": "Orthodox",
  "gender": "MALE",
  "finish_rate_pct": 55.6,
  "wins_ko_tko": 1,
  "wins_submission": 4,
  "wins_decision": 4,
  "current_win_streak": 0,
  "last_fight_date": "2024-11-16",
  "ufcstats_url": "http://ufcstats.com/fighter-details/f4d92416da98804b",
  "nickname": "The Habibi",
  "dob": "Jan 31, 1992",
  "sherdog_record": "N/A",
  "wins_by_ko": 1,
  "wins_by_submission": 4,
  "wins_by_decision": 4,
  "losses_by_ko": 1,
  "losses_by_decision": 4,
  "weight": "170 lbs",
  "nationality": "United States",
  "team": "Elevation Fight Team",
  "fight_history": [
    {
      "result": "loss",
      "opponent": "Oban Elliott",
      "method": "KO (Punches)",
      "method_detail": "Marc Goddard",
      "event": "UFC 309 - Jones vs. Miocic",
      "date": "Nov 16 2024",
      "round": "3",
      "time": "0:40",
      "fight_type": "pro"
    },
    {
      "result": "win",
      "opponent": "Mickey Gall",
      "method": "Decision (Unanimous)",
      "method_detail": "Jason Herzog",
      "event": "UFC 302 - Makhachev vs. Poirier",
      "date": "Jun 01 2024",
      "round": "3",
      "time": "5:00",
      "fight_type": "pro"
    },
    {
      "result": "loss",
      "opponent": "Jack Della Maddalena",
      "method": "Decision (Split)",
      "method_detail": "Mark Smith",
      "event": "UFC on ESPN 49 - Holm vs. Bueno Silva",
      "date": "Jul 15 2023",
      "round": "3",
      "time": "5:00",
      "fight_type": "pro"
    },
    {
      "result": "win",
      "opponent": "Evan Cutts",
      "method": "KO (Punch)",
      "method_detail": "Jeff Rexroad",
      "event": "Fury FC 75 - Fury Fighting Championship 75: Cutts vs. Hafez",
      "date": "Feb 17 2023",
      "round": "3",
      "time": "3:47",
      "fight_type": "pro"
    },
    {
      "result": "win",
      "opponent": "Anthony Ivy",
      "method": "Decision (Split)",
      "method_detail": "Jason Stafin",
      "event": "Fury FC 56 - Fury Fighting Championship 56",
      "date": "Feb 06 2022",
      "round": "3",
      "time": "5:00",
      "fight_type": "pro"
    },
    {
      "result": "loss",
      "opponent": "Evan Cutts",
      "method": "Decision (Split)",
      "method_detail": "Bill Bookwalter",
      "event": "CFFC 94 - Cage Fury Fighting Championships 94",
      "date": "Apr 01 2021",
      "round": "5",
      "time": "5:00",
      "fight_type": "pro"
    },
    {
      "result": "win",
      "opponent": "Christien Savoie",
      "method": "Submission (Triangle Choke)",
      "method_detail": "Dan Miragliotta",
      "event": "CFFC 89 - Cage Fury Fighting Championships 89",
      "date": "Nov 19 2020",
      "round": "1",
      "time": "4:15",
      "fight_type": "pro"
    },
    {
      "result": "win",
      "opponent": "Smith  Amisial",
      "method": "Decision (Unanimous)",
      "method_detail": "Bill Bookwalter",
      "event": "AOW 17 - Art of War Cage Fighting 17: All Star Weekend Day 2",
      "date": "Feb 08 2020",
      "round": "3",
      "time": "5:00",
      "fight_type": "pro"
    },
    {
      "result": "loss",
      "opponent": "Richard Williams",
      "method": "Decision (Split)",
      "method_detail": "Tommy Santana",
      "event": "AFC 9 - Road To The Octagon",
      "date": "Nov 24 2018",
      "round": "3",
      "time": "5:00",
      "fight_type": "pro"
    },
    {
      "result": "win",
      "opponent": "Jerome Mickle",
      "method": "Submission (Kimura)",
      "method_detail": "Dan Miragliotta",
      "event": "Maverick MMA 6 - Birchler vs. Hamill",
      "date": "Apr 14 2018",
      "round": "1",
      "time": "1:01",
      "fight_type": "pro"
    },
    {
      "result": "draw",
      "opponent": "Jeremiah Wells",
      "method": "Draw (Split)",
      "method_detail": "Bill Bookwalter",
      "event": "CFFC 68 - Cage Fury Fighting Championships 68",
      "date": "Oct 21 2017",
      "round": "3",
      "time": "5:00",
      "fight_type": "pro"
    },
    {
      "result": "win",
      "opponent": "Chauncey Foxworth",
      "method": "Submission (Rear-Naked Choke)",
      "method_detail": "",
      "event": "CFFC 65 - Brady vs. Saraceno",
      "date": "May 20 2017",
      "round": "1",
      "time": "1:19",
      "fight_type": "pro"
    },
    {
      "result": "loss",
      "opponent": "De'Alonzio Jackson",
      "method": "Decision (Unanimous)",
      "method_detail": "Keith Peterson",
      "event": "CFFC 61 - Anyanwu vs. Pinto",
      "date": "Oct 29 2016",
      "round": "3",
      "time": "5:00",
      "fight_type": "pro"
    },
    {
      "result": "win",
      "opponent": "Robert Plotkin",
      "method": "Decision (Unanimous)",
      "method_detail": "Dan Miragliotta",
      "event": "CFFC 57 - Gaudinot vs. Honorio",
      "date": "Mar 19 2016",
      "round": "3",
      "time": "5:00",
      "fight_type": "pro"
    },
    {
      "result": "win",
      "opponent": "Kendrick Mendez",
      "method": "Submission (Armbar)",
      "method_detail": "Keith Peterson",
      "event": "CFFC 55 - Chookagian vs. Varela",
      "date": "Jan 09 2016",
      "round": "1",
      "time": "2:02",
      "fight_type": "pro"
    },
    {
      "result": "win",
      "opponent": "Paul Sims",
      "method": "Submission (Rear-Naked Choke)",
      "method_detail": "",
      "event": "CFFC 49 - Honor vs. Oliveira",
      "date": "Jun 06 2015",
      "round": "3",
      "time": "1:30",
      "fight_type": "amateur"
    },
    {
      "result": "win",
      "opponent": "Kristopher Gratalo",
      "method": "Submission (Triangle Choke)",
      "method_detail": "Bill Bookwalter",
      "event": "XFE 42 - Xtreme Fight Events 42",
      "date": "May 10 2014",
      "round": "2",
      "time": "1:08",
      "fight_type": "amateur"
    },
    {
      "result": "loss",
      "opponent": "Joseph Lowry",
      "method": "Decision (Unanimous)",
      "method_detail": "James Chappell",
      "event": "XFE - Cage Wars 27",
      "date": "Oct 19 2013",
      "round": "3",
      "time": "3:00",
      "fight_type": "amateur"
    },
    {
      "result": "win",
      "opponent": "Nicholas Willey",
      "method": "Decision (Split)",
      "method_detail": "James Chappell",
      "event": "XFE - Cage Wars 26",
      "date": "Aug 24 2013",
      "round": "3",
      "time": "3:00",
      "fight_type": "amateur"
    },
    {
      "result": "win",
      "opponent": "Steve Wilson",
      "method": "TKO (Punches)",
      "method_detail": "",
      "event": "XFE - Cage Wars 23",
      "date": "Jun 01 2013",
      "round": "1",
      "time": "1:52",
      "fight_type": "amateur"
    },
    {
      "result": "win",
      "opponent": "Hakeif Phillips",
      "method": "Submission (Keylock)",
      "method_detail": "James Chappell",
      "event": "XFE - Cage Wars 20",
      "date": "Feb 22 2013",
      "round": "1",
      "time": "0:20",
      "fight_type": "amateur"
    },
    {
      "result": "win",
      "opponent": "Christopher Martin",
      "method": "TKO (Punches)",
      "method_detail": "",
      "event": "XFE - Cage Wars 18",
      "date": "Oct 13 2012",
      "round": "3",
      "time": "0:23",
      "fight_type": "amateur"
    }
  ],
  "sherdog_url": "https://www.sherdog.com/fighter/Bassil-Hafez-116663",
  "current_loss_streak": 1,
  "record_last_5": "3-2",
  "age": 34,
  "ufc_image_url": null,
  "stats": {
    "slpm": 3.71,
    "sapm": 5.68,
    "striking_accuracy": "38%",
    "striking_defense": "41%",
    "td_avg": 2.21,
    "td_accuracy": "24%",
    "td_defense": "50%",
    "avg_sub_attempts": 0.0
  },
  "ai_record": null
}