{
  "slug": "damon-blackshear",
  "name": "Da'Mon Blackshear",
  "last_updated": "2026-04-28T17:17:28.263644",
  "weight_class": "Bantamweight",
  "record": "3-3-1",
  "wins": 3,
  "losses": 3,
  "draws": 1,
  "height": "5' 10\"",
  "reach": "72\"",
  "weight_lbs": "135 lbs",
  "stance": "Switch",
  "gender": "MALE",
  "finish_rate_pct": 76.5,
  "wins_ko_tko": 2,
  "wins_submission": 11,
  "wins_decision": 4,
  "current_win_streak": 0,
  "last_fight_date": "2024-11-09",
  "ufcstats_url": "http://ufcstats.com/fighter-details/da22387a0407a2dc",
  "nickname": "The Monster",
  "dob": "Aug 12, 1994",
  "sherdog_record": "N/A",
  "wins_by_ko": 2,
  "wins_by_submission": 11,
  "wins_by_decision": 4,
  "losses_by_ko": 1,
  "losses_by_decision": 7,
  "weight": "135 lbs",
  "nationality": "United States",
  "team": "Kill Cliff FC",
  "fight_history": [
    {
      "result": "loss",
      "opponent": "Davey Grant",
      "method": "Decision (Unanimous)",
      "method_detail": "Jason Herzog",
      "event": "UFC on ABC 9 - Whittaker vs. de Ridder",
      "date": "Jul 26 2025",
      "round": "3",
      "time": "5:00",
      "fight_type": "pro"
    },
    {
      "result": "win",
      "opponent": "Heili Alateng",
      "method": "Decision (Unanimous)",
      "method_detail": "Jason Herzog",
      "event": "UFC on ESPN 66 - Garry vs. Prates",
      "date": "Apr 26 2025",
      "round": "3",
      "time": "5:00",
      "fight_type": "pro"
    },
    {
      "result": "win",
      "opponent": "Cody Gibson",
      "method": "Submission (Kimura)",
      "method_detail": "Chris Tognoni",
      "event": "UFC Fight Night 254 - Vettori vs. Dolidze 2",
      "date": "Mar 15 2025",
      "round": "2",
      "time": "4:09",
      "fight_type": "pro"
    },
    {
      "result": "win",
      "opponent": "Cody Stamann",
      "method": "Submission (Rear-Naked Choke)",
      "method_detail": "Mike Beltran",
      "event": "UFC Fight Night 247 - Magny vs. Prates",
      "date": "Nov 09 2024",
      "round": "1",
      "time": "4:19",
      "fight_type": "pro"
    },
    {
      "result": "loss",
      "opponent": "Montel Jackson",
      "method": "KO (Punch)",
      "method_detail": "Nick Berens",
      "event": "UFC on ESPN 59 - Namajunas vs. Cortez",
      "date": "Jul 13 2024",
      "round": "1",
      "time": "0:18",
      "fight_type": "pro"
    },
    {
      "result": "loss",
      "opponent": "Mario Bautista",
      "method": "Decision (Unanimous)",
      "method_detail": "Bryan Miner",
      "event": "UFC 292 - Sterling vs. O'Malley",
      "date": "Aug 19 2023",
      "round": "3",
      "time": "5:00",
      "fight_type": "pro"
    },
    {
      "result": "win",
      "opponent": "Jose Johnson",
      "method": "Submission (Twister)",
      "method_detail": "Mark Smith",
      "event": "UFC on ESPN 51 - Luque vs. dos Anjos",
      "date": "Aug 12 2023",
      "round": "1",
      "time": "3:47",
      "fight_type": "pro"
    },
    {
      "result": "win",
      "opponent": "Luan Lacerda",
      "method": "TKO (Punches)",
      "method_detail": "Chris Tognoni",
      "event": "UFC on ESPN 46 - Kara-France vs. Albazi",
      "date": "Jun 03 2023",
      "round": "2",
      "time": "3:54",
      "fight_type": "pro"
    },
    {
      "result": "loss",
      "opponent": "Farid Basharat",
      "method": "Decision (Unanimous)",
      "method_detail": "Keith Peterson",
      "event": "UFC 285 - Jones vs. Gane",
      "date": "Mar 04 2023",
      "round": "3",
      "time": "5:00",
      "fight_type": "pro"
    },
    {
      "result": "draw",
      "opponent": "Youssef Zalal",
      "method": "Draw (Majority)",
      "method_detail": "Herb Dean",
      "event": "UFC on ESPN 41 - Vera vs. Cruz",
      "date": "Aug 13 2022",
      "round": "3",
      "time": "5:00",
      "fight_type": "pro"
    },
    {
      "result": "win",
      "opponent": "Josh Smith",
      "method": "Submission (Rear-Naked Choke)",
      "method_detail": "Keith Peterson",
      "event": "CFFC 108 - Cage Fury Fighting Championships 108",
      "date": "May 14 2022",
      "round": "3",
      "time": "2:34",
      "fight_type": "pro"
    },
    {
      "result": "win",
      "opponent": "Deandre Anderson",
      "method": "Submission (Rear-Naked Choke)",
      "method_detail": "Eric McMahon",
      "event": "CFFC 103 - Cage Fury Fighting Championships 103",
      "date": "Nov 19 2021",
      "round": "1",
      "time": "4:33",
      "fight_type": "pro"
    },
    {
      "result": "win",
      "opponent": "Mateo Alejandro Vogel",
      "method": "Decision (Unanimous)",
      "method_detail": "Eric McMahon",
      "event": "CFFC 99 - Cage Fury Fighting Championships 99",
      "date": "Aug 14 2021",
      "round": "3",
      "time": "5:00",
      "fight_type": "pro"
    },
    {
      "result": "win",
      "opponent": "Joseph Penafiel",
      "method": "Submission (Guillotine Choke)",
      "method_detail": "Josh Rutgers",
      "event": "CES MMA 62 - Orlando",
      "date": "Apr 30 2021",
      "round": "3",
      "time": "3:27",
      "fight_type": "pro"
    },
    {
      "result": "loss",
      "opponent": "Danny Sabatello",
      "method": "Decision (Unanimous)",
      "method_detail": "Alan Abeles",
      "event": "Titan FC 67 - Sabatello vs. Blackshear",
      "date": "Feb 12 2021",
      "round": "5",
      "time": "5:00",
      "fight_type": "pro"
    },
    {
      "result": "win",
      "opponent": "Mike Kimbel",
      "method": "Submission (Rear-Naked Choke)",
      "method_detail": "Bryan Miner",
      "event": "Bellator 249 - Cyborg vs. Blencowe",
      "date": "Oct 15 2020",
      "round": "2",
      "time": "4:14",
      "fight_type": "pro"
    },
    {
      "result": "win",
      "opponent": "Kody Nordby",
      "method": "Submission (Arm-Triangle Choke)",
      "method_detail": "Alan Lau",
      "event": "CES MMA 59 - Knight vs. Skipper",
      "date": "Oct 25 2019",
      "round": "2",
      "time": "1:00",
      "fight_type": "pro"
    },
    {
      "result": "loss",
      "opponent": "Pat Sabatini",
      "method": "Decision (Unanimous)",
      "method_detail": "Bill Bookwalter",
      "event": "CFFC 71 - Cage Fury Fighting Championships 71",
      "date": "Dec 14 2018",
      "round": "4",
      "time": "5:00",
      "fight_type": "pro"
    },
    {
      "result": "win",
      "opponent": "Chris Wright",
      "method": "TKO (Punches)",
      "method_detail": "",
      "event": "NLFC - Next Level Fight Club 9",
      "date": "Sep 22 2018",
      "round": "2",
      "time": "3:06",
      "fight_type": "pro"
    },
    {
      "result": "loss",
      "opponent": "Kris Moutinho",
      "method": "Decision (Unanimous)",
      "method_detail": "Kevin MacDonald",
      "event": "CES MMA 51 - Andrews vs. Owens",
      "date": "Aug 03 2018",
      "round": "3",
      "time": "5:00",
      "fight_type": "pro"
    },
    {
      "result": "win",
      "opponent": "Aaron Lacey",
      "method": "Decision (Unanimous)",
      "method_detail": "",
      "event": "NEF 34 - Home of the Brave",
      "date": "Jun 16 2018",
      "round": "3",
      "time": "5:00",
      "fight_type": "pro"
    },
    {
      "result": "loss",
      "opponent": "Keith Richardson",
      "method": "Decision (Split)",
      "method_detail": "",
      "event": "Warfare FC - Warfare MMA 16",
      "date": "Aug 19 2017",
      "round": "5",
      "time": "5:00",
      "fight_type": "pro"
    },
    {
      "result": "win",
      "opponent": "Aalon Cruz",
      "method": "Submission (Rear-Naked Choke)",
      "method_detail": "",
      "event": "Conflict MMA 43 - Conflict MMA Promotions",
      "date": "Jun 24 2017",
      "round": "4",
      "time": "3:09",
      "fight_type": "pro"
    },
    {
      "result": "win",
      "opponent": "Jeremiah Scott",
      "method": "Decision (Unanimous)",
      "method_detail": "",
      "event": "Warfare FC - Warfare MMA 15",
      "date": "May 06 2017",
      "round": "3",
      "time": "5:00",
      "fight_type": "pro"
    },
    {
      "result": "win",
      "opponent": "James Brown",
      "method": "Submission (Rear-Naked Choke)",
      "method_detail": "Joseph Hawes",
      "event": "RDMMA - Battle in the South 13: Summer Stunner",
      "date": "Aug 20 2016",
      "round": "2",
      "time": "2:44",
      "fight_type": "pro"
    },
    {
      "result": "win",
      "opponent": "Kenny Hill",
      "method": "Submission (Triangle Choke)",
      "method_detail": "",
      "event": "RDMMA - Battle in the South 12",
      "date": "Mar 26 2016",
      "round": "2",
      "time": "2:30",
      "fight_type": "pro"
    },
    {
      "result": "win",
      "opponent": "Charleston Pou",
      "method": "Decision (Unanimous)",
      "method_detail": "",
      "event": "Conflict MMA 35 - Live in the Cage",
      "date": "Feb 20 2016",
      "round": "3",
      "time": "3:00",
      "fight_type": "amateur"
    },
    {
      "result": "win",
      "opponent": "Thomas Blair",
      "method": "Submission (Rear Naked Choke)",
      "method_detail": "",
      "event": "SFL 21 - Spartyka Fight League 21: End 22",
      "date": "Nov 07 2015",
      "round": "2",
      "time": "1:32",
      "fight_type": "amateur"
    },
    {
      "result": "loss",
      "opponent": "Tony Gravely",
      "method": "Decision (Unanimous)",
      "method_detail": "Dale Frye",
      "event": "FLP - Fight Lab 50",
      "date": "Sep 19 2015",
      "round": "5",
      "time": "4:00",
      "fight_type": "amateur"
    },
    {
      "result": "win",
      "opponent": "Michael Clippinger",
      "method": "KO",
      "method_detail": "",
      "event": "RDMMA - Battle in the South 11",
      "date": "Aug 01 2015",
      "round": "2",
      "time": "1:21",
      "fight_type": "amateur"
    },
    {
      "result": "win",
      "opponent": "James Adam Ronsick",
      "method": "TKO (Punches)",
      "method_detail": "Dale Frye",
      "event": "FLP - Fight Lab 44: Ft Bragg Army Base MMA Cage Fights",
      "date": "Feb 07 2015",
      "round": "2",
      "time": "0:25",
      "fight_type": "amateur"
    },
    {
      "result": "win",
      "opponent": "Tony Gravely",
      "method": "Decision (Unanimous)",
      "method_detail": "Larry Carter",
      "event": "FLP - Fight Lab 42: MMA Cage Fights @ Grady Cole",
      "date": "Nov 14 2014",
      "round": "3",
      "time": "3:00",
      "fight_type": "amateur"
    },
    {
      "result": "win",
      "opponent": "Shelton Sales",
      "method": "Decision (Unanimous)",
      "method_detail": "Donnie Jessup",
      "event": "FLP - Fight Lab 40: MMA Cage Fights @ Grady Cole",
      "date": "Sep 13 2014",
      "round": "3",
      "time": "3:00",
      "fight_type": "amateur"
    }
  ],
  "sherdog_url": "https://www.sherdog.com/fighter/DaMon-Blackshear-243891",
  "current_loss_streak": 1,
  "record_last_5": "3-2",
  "age": 31,
  "ufc_image_url": "https://www.sherdog.com/image_crop/300/400/_images/fighter/243891_ff.jpg",
  "stats": {
    "slpm": 4.33,
    "sapm": 4.19,
    "striking_accuracy": "45%",
    "striking_defense": "52%",
    "td_avg": 1.48,
    "td_accuracy": "33%",
    "td_defense": "71%",
    "avg_sub_attempts": 1.5
  },
  "ai_record": null
}