{
  "slug": "dan-ige",
  "name": "Dan Ige",
  "last_updated": "2026-04-28T18:46:31.519770",
  "weight_class": "Featherweight",
  "record": "11-8-0",
  "wins": 11,
  "losses": 8,
  "draws": 0,
  "height": "5' 7\"",
  "reach": "71\"",
  "weight_lbs": "145 lbs",
  "stance": "Orthodox",
  "gender": "MALE",
  "finish_rate_pct": 63.2,
  "wins_ko_tko": 7,
  "wins_submission": 5,
  "wins_decision": 7,
  "current_win_streak": 0,
  "last_fight_date": "2024-10-26",
  "ufcstats_url": "http://ufcstats.com/fighter-details/82a5152216251682",
  "nickname": "100K",
  "dob": "Aug 06, 1991",
  "sherdog_record": "N/A",
  "wins_by_ko": 7,
  "wins_by_submission": 5,
  "wins_by_decision": 7,
  "losses_by_ko": 1,
  "losses_by_decision": 10,
  "weight": "145 lbs",
  "nationality": "United States",
  "team": "Xtreme Couture",
  "fight_history": [
    {
      "result": "loss",
      "opponent": "Melquizael Costa",
      "method": "TKO (Spinning Back Kick and Punches)",
      "method_detail": "Jacob Montalvo",
      "event": "UFC Fight Night 267 - Strickland vs. Hernandez",
      "date": "Feb 21 2026",
      "round": "1",
      "time": "4:56",
      "fight_type": "pro"
    },
    {
      "result": "loss",
      "opponent": "Patricio Freire",
      "method": "Decision (Unanimous)",
      "method_detail": "Dan Miragliotta",
      "event": "UFC 318 - Holloway vs. Poirier 3",
      "date": "Jul 19 2025",
      "round": "3",
      "time": "5:00",
      "fight_type": "pro"
    },
    {
      "result": "win",
      "opponent": "Sean Woodson",
      "method": "TKO (Punches)",
      "method_detail": "Andrew Glenn",
      "event": "UFC 314 - Volkanovski vs. Lopes",
      "date": "Apr 12 2025",
      "round": "3",
      "time": "1:12",
      "fight_type": "pro"
    },
    {
      "result": "loss",
      "opponent": "Lerone Murphy",
      "method": "Decision (Unanimous)",
      "method_detail": "Mark Smith",
      "event": "UFC 308 - Topuria vs. Holloway",
      "date": "Oct 26 2024",
      "round": "3",
      "time": "5:00",
      "fight_type": "pro"
    },
    {
      "result": "loss",
      "opponent": "Diego Lopes",
      "method": "Decision (Unanimous)",
      "method_detail": "Jason Herzog",
      "event": "UFC 303 - Pereira vs. Prochazka 2",
      "date": "Jun 29 2024",
      "round": "3",
      "time": "5:00",
      "fight_type": "pro"
    },
    {
      "result": "win",
      "opponent": "Andre Fili",
      "method": "KO (Punches)",
      "method_detail": "Jason Herzog",
      "event": "UFC Fight Night 236 - Hermansson vs. Pyfer",
      "date": "Feb 10 2024",
      "round": "1",
      "time": "2:43",
      "fight_type": "pro"
    },
    {
      "result": "loss",
      "opponent": "Bryce Mitchell",
      "method": "Decision (Unanimous)",
      "method_detail": "Mark Smith",
      "event": "UFC Fight Night 228 - Fiziev vs. Gamrot",
      "date": "Sep 23 2023",
      "round": "3",
      "time": "5:00",
      "fight_type": "pro"
    },
    {
      "result": "win",
      "opponent": "Nate Landwehr",
      "method": "Decision (Unanimous)",
      "method_detail": "Jason Herzog",
      "event": "UFC 289 - Nunes vs. Aldana",
      "date": "Jun 10 2023",
      "round": "3",
      "time": "5:00",
      "fight_type": "pro"
    },
    {
      "result": "win",
      "opponent": "Damon Jackson",
      "method": "KO (Punch)",
      "method_detail": "Jason Herzog",
      "event": "UFC Fight Night 217 - Strickland vs. Imavov",
      "date": "Jan 14 2023",
      "round": "2",
      "time": "4:13",
      "fight_type": "pro"
    },
    {
      "result": "loss",
      "opponent": "Movsar Evloev",
      "method": "Decision (Unanimous)",
      "method_detail": "Keith Peterson",
      "event": "UFC Fight Night 207 - Volkov vs. Rozenstruik",
      "date": "Jun 04 2022",
      "round": "3",
      "time": "5:00",
      "fight_type": "pro"
    },
    {
      "result": "loss",
      "opponent": "Josh Emmett",
      "method": "Decision (Unanimous)",
      "method_detail": "Chris Tognoni",
      "event": "UFC 269 - Oliveira vs. Poirier",
      "date": "Dec 11 2021",
      "round": "3",
      "time": "5:00",
      "fight_type": "pro"
    },
    {
      "result": "loss",
      "opponent": "Chan Sung Jung",
      "method": "Decision (Unanimous)",
      "method_detail": "Herb Dean",
      "event": "UFC on ESPN 25 - Korean Zombie vs. Ige",
      "date": "Jun 19 2021",
      "round": "5",
      "time": "5:00",
      "fight_type": "pro"
    },
    {
      "result": "win",
      "opponent": "Gavin Tucker",
      "method": "KO (Punch)",
      "method_detail": "Mike Beltran",
      "event": "UFC Fight Night 187 - Edwards vs. Muhammad",
      "date": "Mar 13 2021",
      "round": "1",
      "time": "0:22",
      "fight_type": "pro"
    },
    {
      "result": "loss",
      "opponent": "Calvin Kattar",
      "method": "Decision (Unanimous)",
      "method_detail": "Herb Dean",
      "event": "UFC on ESPN 13 - Kattar vs. Ige",
      "date": "Jul 15 2020",
      "round": "5",
      "time": "5:00",
      "fight_type": "pro"
    },
    {
      "result": "win",
      "opponent": "Edson Barboza",
      "method": "Decision (Split)",
      "method_detail": "Jason Herzog",
      "event": "UFC on ESPN 8 - Overeem vs. Harris",
      "date": "May 16 2020",
      "round": "3",
      "time": "5:00",
      "fight_type": "pro"
    },
    {
      "result": "win",
      "opponent": "Mirsad Bektic",
      "method": "Decision (Split)",
      "method_detail": "Kerry Hatley",
      "event": "UFC 247 - Jones vs. Reyes",
      "date": "Feb 08 2020",
      "round": "3",
      "time": "5:00",
      "fight_type": "pro"
    },
    {
      "result": "win",
      "opponent": "Kevin Aguilar",
      "method": "Decision (Unanimous)",
      "method_detail": "Jimmy Neely",
      "event": "UFC Fight Night 154 - Moicano vs. The Korean Zombie",
      "date": "Jun 22 2019",
      "round": "3",
      "time": "5:00",
      "fight_type": "pro"
    },
    {
      "result": "win",
      "opponent": "Danny Henry",
      "method": "Submission (Rear-Naked Choke)",
      "method_detail": "Marc Goddard",
      "event": "UFC Fight Night 147 - Till vs. Masvidal",
      "date": "Mar 16 2019",
      "round": "1",
      "time": "1:17",
      "fight_type": "pro"
    },
    {
      "result": "win",
      "opponent": "Jordan Griffin",
      "method": "Decision (Unanimous)",
      "method_detail": "Joe Fipp",
      "event": "UFC on Fox 31 - Iaquinta vs. Lee 2",
      "date": "Dec 15 2018",
      "round": "3",
      "time": "5:00",
      "fight_type": "pro"
    },
    {
      "result": "win",
      "opponent": "Mike Santiago",
      "method": "TKO (Punches)",
      "method_detail": "Kevin MacDonald",
      "event": "UFC 225 - Whittaker vs. Romero 2",
      "date": "Jun 09 2018",
      "round": "1",
      "time": "0:50",
      "fight_type": "pro"
    },
    {
      "result": "loss",
      "opponent": "Julio Arce",
      "method": "Decision (Unanimous)",
      "method_detail": "Kevin MacDonald",
      "event": "UFC 220 - Miocic vs. Ngannou",
      "date": "Jan 20 2018",
      "round": "3",
      "time": "5:00",
      "fight_type": "pro"
    },
    {
      "result": "win",
      "opponent": "Luis Gomez",
      "method": "Submission (Rear-Naked Choke)",
      "method_detail": "Jason Herzog",
      "event": "Dana White's Tuesday Night Contender Series - Season 1, Episode 3",
      "date": "Jul 25 2017",
      "round": "3",
      "time": "3:23",
      "fight_type": "pro"
    },
    {
      "result": "win",
      "opponent": "Ronildo Augusto Braga",
      "method": "Decision (Unanimous)",
      "method_detail": "Michael Cardoso",
      "event": "Titan FC 44 - Torres vs. Sharipov",
      "date": "May 19 2017",
      "round": "3",
      "time": "5:00",
      "fight_type": "pro"
    },
    {
      "result": "win",
      "opponent": "Fernando Padilla",
      "method": "Decision (Unanimous)",
      "method_detail": "",
      "event": "CFFC 64 - Sayles vs. Aguilera",
      "date": "Mar 25 2017",
      "round": "3",
      "time": "5:00",
      "fight_type": "pro"
    },
    {
      "result": "win",
      "opponent": "Diego Pichilingue",
      "method": "Submission (Kimura)",
      "method_detail": "Kevin Nix",
      "event": "LFC 62 - Legacy Fighting Championship 62",
      "date": "Nov 11 2016",
      "round": "2",
      "time": "0:52",
      "fight_type": "pro"
    },
    {
      "result": "win",
      "opponent": "Craig Campbell",
      "method": "TKO (Punches)",
      "method_detail": "Jordan Bass",
      "event": "LFC 57 - Legacy Fighting Championship 57",
      "date": "Jul 01 2016",
      "round": "1",
      "time": "3:31",
      "fight_type": "pro"
    },
    {
      "result": "win",
      "opponent": "James Jones",
      "method": "TKO (Doctor Stoppage)",
      "method_detail": "Kevin Mulhall",
      "event": "SF - Shogun Fights 14",
      "date": "Apr 16 2016",
      "round": "1",
      "time": "3:56",
      "fight_type": "pro"
    },
    {
      "result": "loss",
      "opponent": "Taichi Nakajima",
      "method": "Decision (Split)",
      "method_detail": "",
      "event": "Pancrase - 272",
      "date": "Nov 28 2015",
      "round": "3",
      "time": "5:00",
      "fight_type": "pro"
    },
    {
      "result": "win",
      "opponent": "Ian Millan",
      "method": "Submission (Rear-Naked Choke)",
      "method_detail": "Herb Dean",
      "event": "RFA 23 - Murphy vs. Ware",
      "date": "Feb 06 2015",
      "round": "1",
      "time": "1:51",
      "fight_type": "pro"
    },
    {
      "result": "win",
      "opponent": "Spencer Higa",
      "method": "Submission (Armbar)",
      "method_detail": "Dayne Furuta",
      "event": "SEC - Star Elite Cage Fighting",
      "date": "Jun 14 2014",
      "round": "3",
      "time": "3:07",
      "fight_type": "pro"
    },
    {
      "result": "win",
      "opponent": "Andrew Fukui",
      "method": "Decision",
      "method_detail": "",
      "event": "Destiny MMA - Na Koa 4",
      "date": "Jan 25 2014",
      "round": "3",
      "time": "3:00",
      "fight_type": "amateur"
    },
    {
      "result": "win",
      "opponent": "Tyrone Henderson",
      "method": "Decision (Unanimous)",
      "method_detail": "Willie Coleman",
      "event": "Star Elite Cage Fighting - Bombs Away",
      "date": "Dec 07 2013",
      "round": "3",
      "time": "3:00",
      "fight_type": "amateur"
    },
    {
      "result": "win",
      "opponent": "Ryan Dela Cruz",
      "method": "Decision (Unanimous)",
      "method_detail": "Abe Rodriguez",
      "event": "Destiny MMA - Proving Grounds",
      "date": "Jun 29 2013",
      "round": "3",
      "time": "3:00",
      "fight_type": "amateur"
    },
    {
      "result": "win",
      "opponent": "Johnny Pecyna",
      "method": "Submission (Triangle Choke)",
      "method_detail": "Kevin Yoshida",
      "event": "Destiny MMA - Na Koa 3",
      "date": "Apr 06 2013",
      "round": "1",
      "time": "2:25",
      "fight_type": "amateur"
    },
    {
      "result": "loss",
      "opponent": "Robby Ostovich",
      "method": "Decision (Unanimous)",
      "method_detail": "Kevin Yoshida",
      "event": "Destiny MMA - Na Koa 1",
      "date": "Sep 08 2012",
      "round": "3",
      "time": "3:00",
      "fight_type": "amateur"
    }
  ],
  "sherdog_url": "https://www.sherdog.com/fighter/Dan-Ige-136499",
  "current_loss_streak": 2,
  "record_last_5": "1-4",
  "age": 34,
  "ufc_image_url": "/images/fighters/dan-ige.jpg",
  "stats": {
    "slpm": 3.6,
    "sapm": 3.56,
    "striking_accuracy": "45%",
    "striking_defense": "56%",
    "td_avg": 0.93,
    "td_accuracy": "26%",
    "td_defense": "56%",
    "avg_sub_attempts": 0.2
  },
  "ai_record": null
}