{
  "slug": "jake-matthews",
  "name": "Jake Matthews",
  "last_updated": "2026-04-28T19:31:48.437070",
  "weight_class": "Welterweight",
  "record": "13-7-0",
  "wins": 13,
  "losses": 7,
  "draws": 0,
  "height": "5' 11\"",
  "reach": "73\"",
  "weight_lbs": "170 lbs",
  "stance": "Orthodox",
  "gender": "MALE",
  "finish_rate_pct": 63.6,
  "wins_ko_tko": 5,
  "wins_submission": 9,
  "wins_decision": 8,
  "current_win_streak": 0,
  "last_fight_date": "2024-06-01",
  "ufcstats_url": "http://ufcstats.com/fighter-details/a845f0735bc67405",
  "nickname": "The Celtic Kid",
  "dob": "Aug 19, 1994",
  "sherdog_record": "22-8-0",
  "wins_by_ko": 5,
  "wins_by_submission": 9,
  "wins_by_decision": 8,
  "losses_by_ko": 1,
  "losses_by_submission": 4,
  "losses_by_decision": 3,
  "weight": "170 lbs",
  "nationality": "Australia",
  "team": "Nexus",
  "fight_history": [
    {
      "result": "loss",
      "opponent": "Neil Magny",
      "method": "Submission (Brabo Choke)",
      "method_detail": "Jim Perdios",
      "event": "UFC Fight Night 260 - Ulberg vs. Reyes",
      "date": "Sep 27 2025",
      "round": "3",
      "time": "3:08",
      "fight_type": "pro"
    },
    {
      "result": "win",
      "opponent": "Chidi Njokuani",
      "method": "Submission (Rear-Naked Choke)",
      "method_detail": "Jimmy Neely",
      "event": "UFC on ESPN 70 - Lewis vs. Teixeira",
      "date": "Jul 12 2025",
      "round": "1",
      "time": "1:09",
      "fight_type": "pro"
    },
    {
      "result": "win",
      "opponent": "Francisco Prado",
      "method": "Decision (Unanimous)",
      "method_detail": "Mike Beltran",
      "event": "UFC 312 - Du Plessis vs. Strickland 2",
      "date": "Feb 08 2025",
      "round": "3",
      "time": "5:00",
      "fight_type": "pro"
    },
    {
      "result": "win",
      "opponent": "Philip Rowe",
      "method": "Decision (Unanimous)",
      "method_detail": "Vitor Ribeiro",
      "event": "UFC 302 - Makhachev vs. Poirier",
      "date": "Jun 01 2024",
      "round": "3",
      "time": "5:00",
      "fight_type": "pro"
    },
    {
      "result": "loss",
      "opponent": "Michael Morales",
      "method": "Decision (Unanimous)",
      "method_detail": "Herb Dean",
      "event": "UFC Fight Night 232 - Allen vs. Craig",
      "date": "Nov 18 2023",
      "round": "3",
      "time": "5:00",
      "fight_type": "pro"
    },
    {
      "result": "win",
      "opponent": "Darrius Flowers",
      "method": "Submission (Rear-Naked Choke)",
      "method_detail": "Tyler Tomlinson",
      "event": "UFC 291 - Poirier vs. Gaethje 2",
      "date": "Jul 29 2023",
      "round": "2",
      "time": "2:37",
      "fight_type": "pro"
    },
    {
      "result": "loss",
      "opponent": "Matthew Semelsberger",
      "method": "Decision (Unanimous)",
      "method_detail": "Herb Dean",
      "event": "UFC Fight Night 216 - Cannonier vs. Strickland",
      "date": "Dec 17 2022",
      "round": "3",
      "time": "5:00",
      "fight_type": "pro"
    },
    {
      "result": "win",
      "opponent": "Andre Fialho",
      "method": "KO (Punches)",
      "method_detail": "Jason Herzog",
      "event": "UFC 275 - Teixeira vs. Prochazka",
      "date": "Jun 12 2022",
      "round": "2",
      "time": "2:24",
      "fight_type": "pro"
    },
    {
      "result": "loss",
      "opponent": "Sean Brady",
      "method": "Submission (Arm-Triangle Choke)",
      "method_detail": "Chris Tognoni",
      "event": "UFC 259 - Blachowicz vs. Adesanya",
      "date": "Mar 06 2021",
      "round": "3",
      "time": "3:28",
      "fight_type": "pro"
    },
    {
      "result": "win",
      "opponent": "Diego Sanchez",
      "method": "Decision (Unanimous)",
      "method_detail": "Jason Herzog",
      "event": "UFC 253 - Adesanya vs. Costa",
      "date": "Sep 26 2020",
      "round": "3",
      "time": "5:00",
      "fight_type": "pro"
    },
    {
      "result": "win",
      "opponent": "Emil Meek",
      "method": "Decision (Unanimous)",
      "method_detail": "John Sharp",
      "event": "UFC Fight Night 168 - Felder vs. Hooker",
      "date": "Feb 23 2020",
      "round": "3",
      "time": "5:00",
      "fight_type": "pro"
    },
    {
      "result": "win",
      "opponent": "Rostem Akman",
      "method": "Decision (Unanimous)",
      "method_detail": "Greg Kleynjans",
      "event": "UFC 243 - Whittaker vs. Adesanya",
      "date": "Oct 05 2019",
      "round": "3",
      "time": "5:00",
      "fight_type": "pro"
    },
    {
      "result": "loss",
      "opponent": "Anthony Rocco Martin",
      "method": "Technical Submission (Anaconda Choke)",
      "method_detail": "Jim Perdios",
      "event": "UFC Fight Night 142 - Dos Santos vs. Tuivasa",
      "date": "Dec 01 2018",
      "round": "3",
      "time": "1:19",
      "fight_type": "pro"
    },
    {
      "result": "win",
      "opponent": "Shinsho Anzai",
      "method": "Technical Submission (Rear-Naked Choke)",
      "method_detail": "Leon Roberts",
      "event": "UFC Fight Night 132 - Cerrone vs. Edwards",
      "date": "Jun 23 2018",
      "round": "1",
      "time": "2:44",
      "fight_type": "pro"
    },
    {
      "result": "win",
      "opponent": "Jingliang Li",
      "method": "Decision (Unanimous)",
      "method_detail": "Mark Simpson",
      "event": "UFC 221 - Romero vs. Rockhold",
      "date": "Feb 10 2018",
      "round": "3",
      "time": "5:00",
      "fight_type": "pro"
    },
    {
      "result": "win",
      "opponent": "Bojan Velickovic",
      "method": "Decision (Split)",
      "method_detail": "Jim Perdios",
      "event": "UFC Fight Night 121 - Werdum vs. Tybura",
      "date": "Nov 18 2017",
      "round": "3",
      "time": "5:00",
      "fight_type": "pro"
    },
    {
      "result": "loss",
      "opponent": "Andrew Holbrook",
      "method": "Decision (Split)",
      "method_detail": "John Sharp",
      "event": "UFC Fight Night 101 - Whittaker vs. Brunson",
      "date": "Nov 26 2016",
      "round": "3",
      "time": "5:00",
      "fight_type": "pro"
    },
    {
      "result": "loss",
      "opponent": "Kevin Lee",
      "method": "TKO (Punches)",
      "method_detail": "Jason Herzog",
      "event": "UFC  - The Ultimate Fighter 23 Finale",
      "date": "Jul 08 2016",
      "round": "1",
      "time": "4:06",
      "fight_type": "pro"
    },
    {
      "result": "win",
      "opponent": "Johnny Case",
      "method": "Submission (Rear-Naked Choke)",
      "method_detail": "John Sharp",
      "event": "UFC Fight Night 85 - Hunt vs. Mir",
      "date": "Mar 19 2016",
      "round": "3",
      "time": "4:45",
      "fight_type": "pro"
    },
    {
      "result": "win",
      "opponent": "Akbarh Arreola",
      "method": "TKO (Doctor Stoppage)",
      "method_detail": "Greg Kleynjans",
      "event": "UFC 193 - Rousey vs. Holm",
      "date": "Nov 14 2015",
      "round": "2",
      "time": "5:00",
      "fight_type": "pro"
    },
    {
      "result": "loss",
      "opponent": "James Vick",
      "method": "Submission (Guillotine Choke)",
      "method_detail": "Steve Perceval",
      "event": "UFC Fight Night 65 - Miocic vs. Hunt",
      "date": "May 10 2015",
      "round": "1",
      "time": "4:53",
      "fight_type": "pro"
    },
    {
      "result": "win",
      "opponent": "Vagner Rocha",
      "method": "Technical Submission (Rear-Naked Choke)",
      "method_detail": "John Sharp",
      "event": "UFC Fight Night 55 - Rockhold vs. Bisping",
      "date": "Nov 07 2014",
      "round": "2",
      "time": "1:52",
      "fight_type": "pro"
    },
    {
      "result": "win",
      "opponent": "Dashon Johnson",
      "method": "Submission (Triangle Choke)",
      "method_detail": "Peter Hickmott",
      "event": "UFC Fight Night 43 - Te Huna vs. Marquardt",
      "date": "Jun 28 2014",
      "round": "3",
      "time": "3:16",
      "fight_type": "pro"
    },
    {
      "result": "win",
      "opponent": "Stuart Dare",
      "method": "Decision (Unanimous)",
      "method_detail": "",
      "event": "Shamrock Events - Kings of Kombat 12",
      "date": "Apr 26 2014",
      "round": "3",
      "time": "5:00",
      "fight_type": "pro"
    },
    {
      "result": "win",
      "opponent": "Dean Purdon",
      "method": "Submission (Rear-Naked Choke)",
      "method_detail": "Greg Kleynjans",
      "event": "AFC 6 - Australian Fighting Championship 6",
      "date": "Aug 24 2013",
      "round": "2",
      "time": "2:42",
      "fight_type": "pro"
    },
    {
      "result": "win",
      "opponent": "Tadija Majic",
      "method": "TKO (Punches)",
      "method_detail": "",
      "event": "Shamrock Events - Night of Mayhem 7",
      "date": "Jun 22 2013",
      "round": "1",
      "time": "N/A",
      "fight_type": "pro"
    },
    {
      "result": "win",
      "opponent": "Luke Jumeau",
      "method": "Submission (Rear-Naked Choke)",
      "method_detail": "Greg Kleynjans",
      "event": "AFC 5 - Australian Fighting Championship 5",
      "date": "May 10 2013",
      "round": "2",
      "time": "1:14",
      "fight_type": "pro"
    },
    {
      "result": "win",
      "opponent": "Callan Potter",
      "method": "Submission (Triangle Armbar)",
      "method_detail": "",
      "event": "Shamrock Events - Night of Mayhem 6",
      "date": "Mar 16 2013",
      "round": "1",
      "time": "1:42",
      "fight_type": "pro"
    },
    {
      "result": "win",
      "opponent": "Jason Zivkovic",
      "method": "TKO (Punches)",
      "method_detail": "Ignatius Misolidis",
      "event": "Shamrock Events - Kings of Kombat 8",
      "date": "Dec 08 2012",
      "round": "1",
      "time": "0:23",
      "fight_type": "pro"
    },
    {
      "result": "win",
      "opponent": "Sam Fiamatai",
      "method": "TKO (Punches)",
      "method_detail": "Ignatius Misolidis",
      "event": "Shamrock Events - Night of Mayhem 5",
      "date": "Sep 15 2012",
      "round": "2",
      "time": "1:47",
      "fight_type": "pro"
    }
  ],
  "sherdog_url": "https://www.sherdog.com/fighter/Jake-Matthews-122139",
  "current_loss_streak": 1,
  "record_last_5": "3-2",
  "age": 31,
  "ufc_image_url": "https://www.sherdog.com/image_crop/300/400/_images/fighter/122139_ff.jpg",
  "stats": {
    "slpm": 3.34,
    "sapm": 2.62,
    "striking_accuracy": "43%",
    "striking_defense": "60%",
    "td_avg": 1.44,
    "td_accuracy": "41%",
    "td_defense": "64%",
    "avg_sub_attempts": 0.8
  },
  "ai_record": null
}