{
  "slug": "jared-gordon",
  "name": "Jared Gordon",
  "last_updated": "2026-04-28T18:29:09.309449",
  "weight_class": "Lightweight",
  "record": "8-6-0",
  "wins": 8,
  "losses": 6,
  "draws": 0,
  "height": "5' 9\"",
  "reach": "68\"",
  "weight_lbs": "155 lbs",
  "stance": "Orthodox",
  "gender": "MALE",
  "finish_rate_pct": 47.6,
  "wins_ko_tko": 8,
  "wins_submission": 2,
  "wins_decision": 11,
  "current_win_streak": 0,
  "last_fight_date": "2024-06-22",
  "ufcstats_url": "http://ufcstats.com/fighter-details/7026eca45f65377b",
  "nickname": "Flash",
  "dob": "Sep 06, 1988",
  "sherdog_record": "21-8-0",
  "wins_by_ko": 8,
  "wins_by_submission": 2,
  "wins_by_decision": 11,
  "losses_by_ko": 5,
  "losses_by_submission": 1,
  "losses_by_decision": 2,
  "weight": "156 lbs",
  "nationality": "United States",
  "team": "Kill Cliff FC",
  "fight_history": [
    {
      "result": "loss",
      "opponent": "Rafa Garcia",
      "method": "TKO (Elbows)",
      "method_detail": "Kerry Hatley",
      "event": "UFC Fight Night 259 - Noche UFC: Lopes vs. Silva",
      "date": "Sep 13 2025",
      "round": "3",
      "time": "2:27",
      "fight_type": "pro"
    },
    {
      "result": "win",
      "opponent": "Thiago Moises",
      "method": "KO (Punches)",
      "method_detail": "Kerry Hatley",
      "event": "UFC Fight Night 256 - Burns vs. Morales",
      "date": "May 17 2025",
      "round": "1",
      "time": "3:37",
      "fight_type": "pro"
    },
    {
      "result": "loss",
      "opponent": "Nasrat Haqparast",
      "method": "Decision (Split)",
      "method_detail": "Rich Mitchell",
      "event": "UFC on ABC 6 - Whittaker vs. Aliskerov",
      "date": "Jun 22 2024",
      "round": "3",
      "time": "5:00",
      "fight_type": "pro"
    },
    {
      "result": "win",
      "opponent": "Mark O. Madsen",
      "method": "TKO (Elbow and Punches)",
      "method_detail": "Marc Goddard",
      "event": "UFC 295 - Prochazka vs. Pereira",
      "date": "Nov 11 2023",
      "round": "1",
      "time": "4:42",
      "fight_type": "pro"
    },
    {
      "result": "nc",
      "opponent": "Bobby Green",
      "method": "No Contest (Accidental Clash of Heads)",
      "method_detail": "Keith Peterson",
      "event": "UFC Fight Night 222 - Pavlovich vs. Blaydes",
      "date": "Apr 22 2023",
      "round": "1",
      "time": "4:35",
      "fight_type": "pro"
    },
    {
      "result": "loss",
      "opponent": "Paddy Pimblett",
      "method": "Decision (Unanimous)",
      "method_detail": "Herb Dean",
      "event": "UFC 282 - Blachowicz vs. Ankalaev",
      "date": "Dec 10 2022",
      "round": "3",
      "time": "5:00",
      "fight_type": "pro"
    },
    {
      "result": "win",
      "opponent": "Leonardo Santos",
      "method": "Decision (Unanimous)",
      "method_detail": "Herb Dean",
      "event": "UFC 278 - Usman vs. Edwards 2",
      "date": "Aug 20 2022",
      "round": "3",
      "time": "5:00",
      "fight_type": "pro"
    },
    {
      "result": "loss",
      "opponent": "Grant Dawson",
      "method": "Submission (Rear-Naked Choke)",
      "method_detail": "Keith Peterson",
      "event": "UFC on ESPN 35 - Font vs. Vera",
      "date": "Apr 30 2022",
      "round": "3",
      "time": "4:11",
      "fight_type": "pro"
    },
    {
      "result": "win",
      "opponent": "Joe Solecki",
      "method": "Decision (Split)",
      "method_detail": "Dan Miragliotta",
      "event": "UFC Fight Night 193 - Santos vs. Walker",
      "date": "Oct 02 2021",
      "round": "3",
      "time": "5:00",
      "fight_type": "pro"
    },
    {
      "result": "win",
      "opponent": "Danny Chavez",
      "method": "Decision (Unanimous)",
      "method_detail": "Herb Dean",
      "event": "UFC Fight Night 185 - Blaydes vs. Lewis",
      "date": "Feb 20 2021",
      "round": "3",
      "time": "5:00",
      "fight_type": "pro"
    },
    {
      "result": "win",
      "opponent": "Chris Fishgold",
      "method": "Decision (Unanimous)",
      "method_detail": "Marc Goddard",
      "event": "UFC on ESPN 13 - Kattar vs. Ige",
      "date": "Jul 15 2020",
      "round": "3",
      "time": "5:00",
      "fight_type": "pro"
    },
    {
      "result": "loss",
      "opponent": "Charles Oliveira",
      "method": "KO (Punches)",
      "method_detail": "Osiris Maia",
      "event": "UFC Fight Night 164 - Blachowicz vs. Jacare",
      "date": "Nov 16 2019",
      "round": "1",
      "time": "1:26",
      "fight_type": "pro"
    },
    {
      "result": "win",
      "opponent": "Dan Moret",
      "method": "Decision (Unanimous)",
      "method_detail": "Herb Dean",
      "event": "UFC on ESPN 3 - Ngannou vs. Dos Santos",
      "date": "Jun 29 2019",
      "round": "3",
      "time": "5:00",
      "fight_type": "pro"
    },
    {
      "result": "loss",
      "opponent": "Joaquim Silva",
      "method": "KO (Punches)",
      "method_detail": "Rob Hinds",
      "event": "UFC on Fox 31 - Iaquinta vs. Lee 2",
      "date": "Dec 15 2018",
      "round": "3",
      "time": "2:39",
      "fight_type": "pro"
    },
    {
      "result": "loss",
      "opponent": "Diego Ferreira",
      "method": "TKO (Punches)",
      "method_detail": "Dan Miragliotta",
      "event": "UFC Fight Night 126 - Cerrone vs. Medeiros",
      "date": "Feb 18 2018",
      "round": "1",
      "time": "1:58",
      "fight_type": "pro"
    },
    {
      "result": "win",
      "opponent": "Hacran Dias",
      "method": "Decision (Unanimous)",
      "method_detail": "Fernando Portella",
      "event": "UFC Fight Night 119 - Brunson vs. Machida",
      "date": "Oct 28 2017",
      "round": "3",
      "time": "5:00",
      "fight_type": "pro"
    },
    {
      "result": "win",
      "opponent": "Michel Quinones",
      "method": "TKO (Punches)",
      "method_detail": "Keith Peterson",
      "event": "UFC Fight Night 112 - Chiesa vs. Lee",
      "date": "Jun 25 2017",
      "round": "2",
      "time": "4:24",
      "fight_type": "pro"
    },
    {
      "result": "win",
      "opponent": "Bill Algeo",
      "method": "Decision (Unanimous)",
      "method_detail": "Gasper Oliver",
      "event": "CFFC 63 - Anyanwu vs. Teed",
      "date": "Feb 18 2017",
      "round": "4",
      "time": "5:00",
      "fight_type": "pro"
    },
    {
      "result": "win",
      "opponent": "Dawond Pickney",
      "method": "Submission (Rear-Naked Choke)",
      "method_detail": "Gasper Oliver",
      "event": "CFFC 60 - Webb vs. Steele",
      "date": "Aug 06 2016",
      "round": "2",
      "time": "3:10",
      "fight_type": "pro"
    },
    {
      "result": "win",
      "opponent": "Anthony Morrison",
      "method": "KO (Head Kick)",
      "method_detail": "",
      "event": "CFFC 59 - Morrison vs. Gordon",
      "date": "Jul 09 2016",
      "round": "1",
      "time": "1:48",
      "fight_type": "pro"
    },
    {
      "result": "loss",
      "opponent": "Jeff Lentz",
      "method": "TKO (Doctor Stoppage)",
      "method_detail": "Gary Copeland",
      "event": "CFFC 48 - Good vs. Burrell",
      "date": "May 09 2015",
      "round": "3",
      "time": "5:00",
      "fight_type": "pro"
    },
    {
      "result": "win",
      "opponent": "Jay Coleman",
      "method": "TKO (Punches)",
      "method_detail": "Vitor Ribeiro",
      "event": "CFFC 45 - Stiner vs. Horcher",
      "date": "Feb 07 2015",
      "round": "1",
      "time": "4:47",
      "fight_type": "pro"
    },
    {
      "result": "win",
      "opponent": "Corey Bleaken",
      "method": "Decision (Unanimous)",
      "method_detail": "",
      "event": "CFFC 44 - Bezerra vs. Makashvili 2",
      "date": "Dec 13 2014",
      "round": "3",
      "time": "5:00",
      "fight_type": "pro"
    },
    {
      "result": "win",
      "opponent": "Johnson Jajoute",
      "method": "Decision (Unanimous)",
      "method_detail": "Gasper Oliver",
      "event": "CFFC 28 - Brenneman vs. Baker",
      "date": "Oct 26 2013",
      "round": "3",
      "time": "5:00",
      "fight_type": "pro"
    },
    {
      "result": "win",
      "opponent": "Alejandro Roman",
      "method": "Decision (Unanimous)",
      "method_detail": "",
      "event": "Duelo De Giagantes - Round 4",
      "date": "Jun 22 2013",
      "round": "5",
      "time": "5:00",
      "fight_type": "pro"
    },
    {
      "result": "win",
      "opponent": "Luiz Gustavo Felix dos Santos",
      "method": "Decision (Unanimous)",
      "method_detail": "",
      "event": "Duelo De Giagantes - Round 3",
      "date": "Jun 15 2013",
      "round": "3",
      "time": "5:00",
      "fight_type": "pro"
    },
    {
      "result": "win",
      "opponent": "Oscar De La Parra",
      "method": "TKO (Punches)",
      "method_detail": "",
      "event": "Duelo De Giagantes - Round 2",
      "date": "Jun 08 2013",
      "round": "3",
      "time": "2:14",
      "fight_type": "pro"
    },
    {
      "result": "win",
      "opponent": "Alvaro Enriquez",
      "method": "TKO (Punches)",
      "method_detail": "",
      "event": "Duelo De Giagantes - Round 1",
      "date": "Jun 02 2013",
      "round": "2",
      "time": "4:25",
      "fight_type": "pro"
    },
    {
      "result": "win",
      "opponent": "Robert Fabrizi",
      "method": "TKO (Punches)",
      "method_detail": "Kevin Mulhall",
      "event": "CFFC 19 - Sullivan vs. Lane",
      "date": "Feb 02 2013",
      "round": "2",
      "time": "2:31",
      "fight_type": "pro"
    },
    {
      "result": "win",
      "opponent": "Anthony D'Agostino",
      "method": "Submission (Rear-Naked Choke)",
      "method_detail": "Donnie Carolei",
      "event": "CFFC 6 - The Return",
      "date": "Feb 05 2011",
      "round": "2",
      "time": "1:42",
      "fight_type": "pro"
    },
    {
      "result": "loss",
      "opponent": "Robert Fabrizi",
      "method": "Decision (Split)",
      "method_detail": "Donnie Carolei",
      "event": "Evolution  - AMMA",
      "date": "Dec 04 2010",
      "round": "3",
      "time": "3:00",
      "fight_type": "amateur"
    },
    {
      "result": "win",
      "opponent": "Julian Przybylski",
      "method": "Decision (Unanimous)",
      "method_detail": "",
      "event": "CITC - Rumble in Rahway 5",
      "date": "Sep 15 2007",
      "round": "3",
      "time": "3:00",
      "fight_type": "amateur"
    }
  ],
  "sherdog_url": "https://www.sherdog.com/fighter/Jared-Gordon-74057",
  "current_loss_streak": 1,
  "record_last_5": "2-3",
  "age": 37,
  "ufc_image_url": "https://www.sherdog.com/image_crop/300/400/_images/fighter/74057_ff.jpg",
  "stats": {
    "slpm": 5.64,
    "sapm": 4.14,
    "striking_accuracy": "53%",
    "striking_defense": "55%",
    "td_avg": 1.78,
    "td_accuracy": "32%",
    "td_defense": "60%",
    "avg_sub_attempts": 0.0
  },
  "ai_record": null
}