{
  "slug": "jonathan-pearce",
  "name": "Jonathan Pearce",
  "last_updated": "2026-04-28T20:12:57.576549",
  "weight_class": "Featherweight",
  "record": "6-4-0",
  "wins": 6,
  "losses": 4,
  "draws": 0,
  "height": "6' 0\"",
  "reach": "71\"",
  "weight_lbs": "145 lbs",
  "stance": "Switch",
  "gender": "MALE",
  "finish_rate_pct": 78.6,
  "wins_ko_tko": 9,
  "wins_submission": 2,
  "wins_decision": 3,
  "current_win_streak": 0,
  "last_fight_date": "2024-10-12",
  "ufcstats_url": "http://ufcstats.com/fighter-details/87c0b1c696ddfb43",
  "nickname": "JSP",
  "dob": "May 01, 1992",
  "sherdog_record": "N/A",
  "wins_by_ko": 9,
  "wins_by_submission": 2,
  "wins_by_decision": 3,
  "losses_by_ko": 1,
  "losses_by_submission": 4,
  "losses_by_decision": 2,
  "weight": "145 lbs",
  "nationality": "United States",
  "team": "Fight Ready",
  "fight_history": [
    {
      "result": "loss",
      "opponent": "Pat Sabatini",
      "method": "Submission (Rear-Naked Choke)",
      "method_detail": "Chris Tognoni",
      "event": "UFC Fight Night 244 - Royval vs. Taira",
      "date": "Oct 12 2024",
      "round": "1",
      "time": "4:06",
      "fight_type": "pro"
    },
    {
      "result": "loss",
      "opponent": "David Onama",
      "method": "Decision (Unanimous)",
      "method_detail": "Chris Tognoni",
      "event": "UFC on ESPN 55 - Nicolau vs. Perez",
      "date": "Apr 27 2024",
      "round": "3",
      "time": "5:00",
      "fight_type": "pro"
    },
    {
      "result": "loss",
      "opponent": "Joanderson Brito",
      "method": "Submission (Ninja Choke)",
      "method_detail": "Herb Dean",
      "event": "UFC Fight Night 232 - Allen vs. Craig",
      "date": "Nov 18 2023",
      "round": "2",
      "time": "3:54",
      "fight_type": "pro"
    },
    {
      "result": "win",
      "opponent": "Darren Elkins",
      "method": "Decision (Unanimous)",
      "method_detail": "Dan Miragliotta",
      "event": "UFC on ESPN 42 - Thompson vs. Holland",
      "date": "Dec 03 2022",
      "round": "3",
      "time": "5:00",
      "fight_type": "pro"
    },
    {
      "result": "win",
      "opponent": "Makwan Amirkhani",
      "method": "TKO (Punches)",
      "method_detail": "Daniel Movahedi",
      "event": "UFC Fight Night 208 - Blaydes vs. Aspinall",
      "date": "Jul 23 2022",
      "round": "2",
      "time": "4:10",
      "fight_type": "pro"
    },
    {
      "result": "win",
      "opponent": "Christian Rodriguez",
      "method": "Decision (Unanimous)",
      "method_detail": "Jason Herzog",
      "event": "UFC Fight Night 201 - Walker vs. Hill",
      "date": "Feb 19 2022",
      "round": "3",
      "time": "5:00",
      "fight_type": "pro"
    },
    {
      "result": "win",
      "opponent": "Omar Morales",
      "method": "Submission (Rear-Naked Choke)",
      "method_detail": "Chris Tognoni",
      "event": "UFC 266 - Volkanovski vs. Ortega",
      "date": "Sep 25 2021",
      "round": "2",
      "time": "3:31",
      "fight_type": "pro"
    },
    {
      "result": "win",
      "opponent": "Kai Kamaka III",
      "method": "TKO (Punches)",
      "method_detail": "Dan Miragliotta",
      "event": "UFC on ESPN 18 - Smith vs. Clark",
      "date": "Nov 28 2020",
      "round": "2",
      "time": "4:28",
      "fight_type": "pro"
    },
    {
      "result": "loss",
      "opponent": "Joe Lauzon",
      "method": "TKO (Punches)",
      "method_detail": "Herb Dean",
      "event": "UFC on ESPN 6 - Reyes vs. Weidman",
      "date": "Oct 18 2019",
      "round": "1",
      "time": "1:33",
      "fight_type": "pro"
    },
    {
      "result": "win",
      "opponent": "Jacob Rosales",
      "method": "TKO (Punch)",
      "method_detail": "Herb Dean",
      "event": "Dana White's Contender Series - Season 3, Episode 3",
      "date": "Jul 09 2019",
      "round": "3",
      "time": "1:50",
      "fight_type": "pro"
    },
    {
      "result": "win",
      "opponent": "Dedrek Sanders",
      "method": "TKO (Doctor Stoppage)",
      "method_detail": "Bill Clancy",
      "event": "Warrior FC 140 - Warrior Fighting Challenge",
      "date": "Sep 21 2018",
      "round": "2",
      "time": "5:00",
      "fight_type": "pro"
    },
    {
      "result": "win",
      "opponent": "Nick Baker",
      "method": "TKO (Punches)",
      "method_detail": "",
      "event": "Valor Fights - Strikefest 2",
      "date": "Dec 16 2017",
      "round": "2",
      "time": "1:12",
      "fight_type": "pro"
    },
    {
      "result": "win",
      "opponent": "Omar Johnson",
      "method": "TKO (Punches)",
      "method_detail": "Blake Grice",
      "event": "Bellator MMA - Alabama 500",
      "date": "Oct 13 2017",
      "round": "2",
      "time": "3:57",
      "fight_type": "pro"
    },
    {
      "result": "win",
      "opponent": "Damir Ferhatbegovic",
      "method": "Submission (Rear-Naked Choke)",
      "method_detail": "Blake Grice",
      "event": "Bellator MMA - Bass Pro Shops NRA Night Race",
      "date": "Aug 19 2017",
      "round": "3",
      "time": "0:43",
      "fight_type": "pro"
    },
    {
      "result": "loss",
      "opponent": "Peter Petties",
      "method": "Decision (Unanimous)",
      "method_detail": "Fernando Yamasaki",
      "event": "SF - Shogun Fights 16",
      "date": "Apr 08 2017",
      "round": "3",
      "time": "5:00",
      "fight_type": "pro"
    },
    {
      "result": "loss",
      "opponent": "Quinten Culpepper",
      "method": "Submission (Toe Hold)",
      "method_detail": "",
      "event": "Valor Fights 37 - Grun vs. Anders",
      "date": "Aug 27 2016",
      "round": "1",
      "time": "3:27",
      "fight_type": "pro"
    },
    {
      "result": "loss",
      "opponent": "Lance Lawrence",
      "method": "Submission (Rear-Naked Choke)",
      "method_detail": "",
      "event": "VF - Valor Fights 35",
      "date": "Jun 25 2016",
      "round": "1",
      "time": "0:24",
      "fight_type": "pro"
    },
    {
      "result": "win",
      "opponent": "Nickalas Martino",
      "method": "TKO (Elbows)",
      "method_detail": "",
      "event": "Valor Fights - Apex Fights 10",
      "date": "Mar 19 2016",
      "round": "2",
      "time": "2:52",
      "fight_type": "pro"
    },
    {
      "result": "win",
      "opponent": "Chris Wright",
      "method": "TKO (Punches)",
      "method_detail": "",
      "event": "Valor Fights 26 - All Pro Tri Cities",
      "date": "Sep 12 2015",
      "round": "1",
      "time": "4:26",
      "fight_type": "pro"
    },
    {
      "result": "win",
      "opponent": "Anthony Morgan",
      "method": "Decision (Unanimous)",
      "method_detail": "Jimmy Neely",
      "event": "Valor Fights - Valor Fights 23",
      "date": "Jun 06 2015",
      "round": "3",
      "time": "5:00",
      "fight_type": "pro"
    },
    {
      "result": "win",
      "opponent": "Noe Quintanilla",
      "method": "KO (Knee)",
      "method_detail": "",
      "event": "ECSS - Evolution Combat Sports Series 2",
      "date": "Nov 08 2014",
      "round": "3",
      "time": "0:22",
      "fight_type": "pro"
    },
    {
      "result": "win",
      "opponent": "Cody Dockery",
      "method": "TKO (Slam and Punches)",
      "method_detail": "",
      "event": "3FC 15 - Townsend vs. Mays",
      "date": "Jan 05 2013",
      "round": "1",
      "time": "2:23",
      "fight_type": "amateur"
    }
  ],
  "sherdog_url": "https://www.sherdog.com/fighter/Jonathan-Pearce-183541",
  "current_loss_streak": 3,
  "record_last_5": "2-3",
  "age": 33,
  "ufc_image_url": "/images/fighters/jonathan-pearce.jpg",
  "stats": {
    "slpm": 5.12,
    "sapm": 3.32,
    "striking_accuracy": "54%",
    "striking_defense": "54%",
    "td_avg": 5.02,
    "td_accuracy": "50%",
    "td_defense": "55%",
    "avg_sub_attempts": 0.8
  },
  "ai_record": null
}