{
  "slug": "sean-strickland",
  "name": "Sean Strickland",
  "last_updated": "2026-04-28T22:25:17.090689",
  "weight_class": "Middleweight",
  "record": "16-6-0",
  "wins": 16,
  "losses": 6,
  "draws": 0,
  "height": "6' 1\"",
  "reach": "76\"",
  "weight_lbs": "185 lbs",
  "stance": "Orthodox",
  "gender": "MALE",
  "finish_rate_pct": 53.3,
  "wins_ko_tko": 12,
  "wins_submission": 4,
  "wins_decision": 14,
  "current_win_streak": 1,
  "last_fight_date": "2024-06-01",
  "ufcstats_url": "http://ufcstats.com/fighter-details/0d8011111be000b2",
  "dob": "Feb 27, 1991",
  "sherdog_record": "30-7-0",
  "wins_by_ko": 12,
  "wins_by_submission": 4,
  "wins_by_decision": 14,
  "losses_by_ko": 2,
  "losses_by_decision": 5,
  "weight": "185 lbs",
  "nationality": "United States",
  "team": "Xtreme Couture",
  "fight_history": [
    {
      "result": "win",
      "opponent": "Anthony Hernandez",
      "method": "TKO (Punches)",
      "method_detail": "Herb Dean",
      "event": "UFC Fight Night 267 - Strickland vs. Hernandez",
      "date": "Feb 21 2026",
      "round": "3",
      "time": "2:23",
      "fight_type": "pro"
    },
    {
      "result": "loss",
      "opponent": "Dricus Du Plessis",
      "method": "Decision (Unanimous)",
      "method_detail": "Marc Goddard",
      "event": "UFC 312 - Du Plessis vs. Strickland 2",
      "date": "Feb 08 2025",
      "round": "5",
      "time": "5:00",
      "fight_type": "pro"
    },
    {
      "result": "win",
      "opponent": "Paulo Costa",
      "method": "Decision (Split)",
      "method_detail": "Jason Herzog",
      "event": "UFC 302 - Makhachev vs. Poirier",
      "date": "Jun 01 2024",
      "round": "5",
      "time": "5:00",
      "fight_type": "pro"
    },
    {
      "result": "loss",
      "opponent": "Dricus Du Plessis",
      "method": "Decision (Split)",
      "method_detail": "Marc Goddard",
      "event": "UFC 297 - Strickland vs. Du Plessis",
      "date": "Jan 20 2024",
      "round": "5",
      "time": "5:00",
      "fight_type": "pro"
    },
    {
      "result": "win",
      "opponent": "Israel Adesanya",
      "method": "Decision (Unanimous)",
      "method_detail": "Marc Goddard",
      "event": "UFC 293 - Adesanya vs. Strickland",
      "date": "Sep 09 2023",
      "round": "5",
      "time": "5:00",
      "fight_type": "pro"
    },
    {
      "result": "win",
      "opponent": "Abusupiyan Magomedov",
      "method": "TKO (Punches)",
      "method_detail": "Mark Smith",
      "event": "UFC on ESPN 48 - Strickland vs. Magomedov",
      "date": "Jul 01 2023",
      "round": "2",
      "time": "4:20",
      "fight_type": "pro"
    },
    {
      "result": "win",
      "opponent": "Nassourdine Imavov",
      "method": "Decision (Unanimous)",
      "method_detail": "Mark Smith",
      "event": "UFC Fight Night 217 - Strickland vs. Imavov",
      "date": "Jan 14 2023",
      "round": "5",
      "time": "5:00",
      "fight_type": "pro"
    },
    {
      "result": "loss",
      "opponent": "Jared Cannonier",
      "method": "Decision (Split)",
      "method_detail": "Herb Dean",
      "event": "UFC Fight Night 216 - Cannonier vs. Strickland",
      "date": "Dec 17 2022",
      "round": "5",
      "time": "5:00",
      "fight_type": "pro"
    },
    {
      "result": "loss",
      "opponent": "Alex Pereira",
      "method": "KO (Punches)",
      "method_detail": "Jason Herzog",
      "event": "UFC 276 - Adesanya vs. Cannonier",
      "date": "Jul 02 2022",
      "round": "1",
      "time": "2:36",
      "fight_type": "pro"
    },
    {
      "result": "win",
      "opponent": "Jack Hermansson",
      "method": "Decision (Split)",
      "method_detail": "Herb Dean",
      "event": "UFC Fight Night 200 - Hermansson vs. Strickland",
      "date": "Feb 05 2022",
      "round": "5",
      "time": "5:00",
      "fight_type": "pro"
    },
    {
      "result": "win",
      "opponent": "Uriah Hall",
      "method": "Decision (Unanimous)",
      "method_detail": "Herb Dean",
      "event": "UFC on ESPN 28 - Hall vs. Strickland",
      "date": "Jul 31 2021",
      "round": "5",
      "time": "5:00",
      "fight_type": "pro"
    },
    {
      "result": "win",
      "opponent": "Krzysztof Jotko",
      "method": "Decision (Unanimous)",
      "method_detail": "Herb Dean",
      "event": "UFC on ESPN 23 - Reyes vs. Prochazka",
      "date": "May 01 2021",
      "round": "3",
      "time": "5:00",
      "fight_type": "pro"
    },
    {
      "result": "win",
      "opponent": "Brendan Allen",
      "method": "TKO (Punches)",
      "method_detail": "Herb Dean",
      "event": "UFC Fight Night 182 - Felder vs. dos Anjos",
      "date": "Nov 14 2020",
      "round": "2",
      "time": "1:32",
      "fight_type": "pro"
    },
    {
      "result": "win",
      "opponent": "Jack Marshman",
      "method": "Decision (Unanimous)",
      "method_detail": "Keith Peterson",
      "event": "UFC Fight Night 181 - Hall vs. Silva",
      "date": "Oct 31 2020",
      "round": "3",
      "time": "5:00",
      "fight_type": "pro"
    },
    {
      "result": "win",
      "opponent": "Nordine Taleb",
      "method": "TKO (Punches)",
      "method_detail": "Eric Nevitt",
      "event": "UFC Fight Night 138 - Oezdemir vs. Smith",
      "date": "Oct 27 2018",
      "round": "2",
      "time": "3:10",
      "fight_type": "pro"
    },
    {
      "result": "loss",
      "opponent": "Elizeu Zaleski dos Santos",
      "method": "KO (Spinning Wheel Kick and Punches)",
      "method_detail": "Fernando Portella",
      "event": "UFC 224 - Nunes vs. Pennington",
      "date": "May 12 2018",
      "round": "1",
      "time": "3:40",
      "fight_type": "pro"
    },
    {
      "result": "win",
      "opponent": "Court McGee",
      "method": "Decision (Unanimous)",
      "method_detail": "Elvis Bello",
      "event": "UFC Fight Night 120 - Poirier vs. Pettis",
      "date": "Nov 11 2017",
      "round": "3",
      "time": "5:00",
      "fight_type": "pro"
    },
    {
      "result": "loss",
      "opponent": "Kamaru Usman",
      "method": "Decision (Unanimous)",
      "method_detail": "Keith Peterson",
      "event": "UFC 210 - Cormier vs. Johnson 2",
      "date": "Apr 08 2017",
      "round": "3",
      "time": "5:00",
      "fight_type": "pro"
    },
    {
      "result": "win",
      "opponent": "Tom Breese",
      "method": "Decision (Split)",
      "method_detail": "Herb Dean",
      "event": "UFC 199 - Rockhold vs. Bisping 2",
      "date": "Jun 04 2016",
      "round": "3",
      "time": "5:00",
      "fight_type": "pro"
    },
    {
      "result": "win",
      "opponent": "Alex Garcia",
      "method": "TKO (Punches)",
      "method_detail": "Bill Bookwalter",
      "event": "UFC Fight Night 83 - Cerrone vs. Oliveira",
      "date": "Feb 21 2016",
      "round": "3",
      "time": "4:25",
      "fight_type": "pro"
    },
    {
      "result": "win",
      "opponent": "Igor Araujo",
      "method": "Decision (Unanimous)",
      "method_detail": "John McCarthy",
      "event": "UFC Fight Night 71 - Mir vs. Duffee",
      "date": "Jul 15 2015",
      "round": "3",
      "time": "5:00",
      "fight_type": "pro"
    },
    {
      "result": "loss",
      "opponent": "Santiago Ponzinibbio",
      "method": "Decision (Unanimous)",
      "method_detail": "Wernei Cardoso",
      "event": "UFC Fight Night 61 - Bigfoot vs. Mir",
      "date": "Feb 22 2015",
      "round": "3",
      "time": "5:00",
      "fight_type": "pro"
    },
    {
      "result": "win",
      "opponent": "Luke Barnatt",
      "method": "Decision (Split)",
      "method_detail": "Grant Waterman",
      "event": "UFC Fight Night 41 - Munoz vs. Mousasi",
      "date": "May 31 2014",
      "round": "3",
      "time": "5:00",
      "fight_type": "pro"
    },
    {
      "result": "win",
      "opponent": "Bubba McDaniel",
      "method": "Submission (Rear-Naked Choke)",
      "method_detail": "Kerry Hatley",
      "event": "UFC 171 - Hendricks vs. Lawler",
      "date": "Mar 15 2014",
      "round": "1",
      "time": "4:33",
      "fight_type": "pro"
    },
    {
      "result": "win",
      "opponent": "Matt Lagler",
      "method": "TKO (Punches)",
      "method_detail": "John McCarthy",
      "event": "KOTC - Split Decision",
      "date": "Aug 29 2013",
      "round": "1",
      "time": "4:59",
      "fight_type": "pro"
    },
    {
      "result": "win",
      "opponent": "Yusuke Sakashita",
      "method": "Decision (Unanimous)",
      "method_detail": "",
      "event": "KOTC - Worldwide",
      "date": "Jul 05 2013",
      "round": "5",
      "time": "5:00",
      "fight_type": "pro"
    },
    {
      "result": "win",
      "opponent": "Bill Albrecht",
      "method": "KO (Punch)",
      "method_detail": "Herb Dean",
      "event": "KOTC - Restitution",
      "date": "Feb 07 2013",
      "round": "1",
      "time": "2:41",
      "fight_type": "pro"
    },
    {
      "result": "win",
      "opponent": "Josh Bryant",
      "method": "Decision (Split)",
      "method_detail": "",
      "event": "KOTC - Unification",
      "date": "Dec 08 2012",
      "round": "3",
      "time": "5:00",
      "fight_type": "pro"
    },
    {
      "result": "win",
      "opponent": "Brandon Hunt",
      "method": "TKO (Punches)",
      "method_detail": "Mike Beltran",
      "event": "KOTC - Hardcore",
      "date": "Apr 26 2012",
      "round": "1",
      "time": "3:24",
      "fight_type": "pro"
    },
    {
      "result": "win",
      "opponent": "Brandon Hunt",
      "method": "TKO (Punches)",
      "method_detail": "",
      "event": "KOTC - Steel Curtain",
      "date": "Dec 17 2011",
      "round": "1",
      "time": "3:48",
      "fight_type": "pro"
    },
    {
      "result": "win",
      "opponent": "Brett Sbardella",
      "method": "KO (Punches)",
      "method_detail": "",
      "event": "KOTC - Demolition",
      "date": "Aug 06 2011",
      "round": "1",
      "time": "1:03",
      "fight_type": "pro"
    },
    {
      "result": "win",
      "opponent": "Donavin Hawkey",
      "method": "Submission (Rear-Naked Choke)",
      "method_detail": "",
      "event": "KOTC - Platinum",
      "date": "Nov 25 2010",
      "round": "1",
      "time": "1:21",
      "fight_type": "pro"
    },
    {
      "result": "win",
      "opponent": "Adriel Montes",
      "method": "TKO (Punches)",
      "method_detail": "",
      "event": "KOTC - Underground 63",
      "date": "Oct 02 2010",
      "round": "2",
      "time": "1:05",
      "fight_type": "pro"
    },
    {
      "result": "win",
      "opponent": "George Interiano",
      "method": "Decision (Unanimous)",
      "method_detail": "Cecil Peoples",
      "event": "LBFN 7 - Long Beach Fight Night 7",
      "date": "Jan 03 2010",
      "round": "3",
      "time": "3:00",
      "fight_type": "pro"
    },
    {
      "result": "win",
      "opponent": "William Wheeler",
      "method": "Submission (Rear-Naked Choke)",
      "method_detail": "",
      "event": "KOTC - Jolted",
      "date": "Oct 03 2009",
      "round": "1",
      "time": "1:55",
      "fight_type": "pro"
    },
    {
      "result": "win",
      "opponent": "Brandon Ellsworth",
      "method": "TKO (Punches)",
      "method_detail": "",
      "event": "KOTC - Last Resort",
      "date": "Mar 14 2009",
      "round": "1",
      "time": "1:28",
      "fight_type": "pro"
    },
    {
      "result": "win",
      "opponent": "Tyler Pottett",
      "method": "Submission (Rear-Naked Choke)",
      "method_detail": "",
      "event": "KOTC - Protege",
      "date": "Mar 22 2008",
      "round": "2",
      "time": "1:53",
      "fight_type": "pro"
    }
  ],
  "sherdog_url": "https://www.sherdog.com/fighter/Sean-Strickland-30452",
  "current_loss_streak": 0,
  "record_last_5": "3-2",
  "age": 35,
  "ufc_image_url": "https://www.sherdog.com/image_crop/300/400/_images/fighter/30452_ff.jpg",
  "stats": {
    "slpm": 6.04,
    "sapm": 4.57,
    "striking_accuracy": "42%",
    "striking_defense": "60%",
    "td_avg": 0.71,
    "td_accuracy": "64%",
    "td_defense": "76%",
    "avg_sub_attempts": 0.2
  },
  "ai_record": null
}